dbview/__init__.py
dbview/db2py.py
dbview/db2txt.py
dbview/get_columns.py
dbview/get_info.py
dbview/get_tables.py
dbview/organize.py
dbview/setup.py
dbview/txt2db.py
dbview/txt2py.py
dbview-3.0.0.dist-info/METADATA
dbview-3.0.0.dist-info/WHEEL
dbview-3.0.0.dist-info/top_level.txt
dbview-3.0.0.dist-info/RECORD
