Metadata-Version: 2.1
Name: dbview
Version: 3.0.0
Summary: DB Viewer -- Quickly view and edit SQLite databases and tables
Home-page: https://github.com/TvoozMagnificent/dbview
Author: TvoozMagnificent
Author-email: luchang1106@icloud.com
License: MIT
Platform: UNKNOWN
Classifier: License :: OSI Approved :: MIT License
Classifier: Programming Language :: Python :: 3
Classifier: Programming Language :: Python :: 3.7
